{
  "package_name": "notoken887-1.26.37",
  "is_malicious": true,
  "files_analyzed": 4,
  "malicious_files": 1,
  "file_results": [
    {
      "file_path": "/home2/wenbo/Documents/PyPIAgent/Dataset/latest/unzip_malware/notoken887-1.26.37/notoken887-1.26.37/notoken887-1.26.37/setup.py",
      "relative_path": "notoken887-1.26.37/notoken887-1.26.37/setup.py",
      "is_malicious": false,
      "malicious_behavior": ""
    },
    {
      "file_path": "/home2/wenbo/Documents/PyPIAgent/Dataset/latest/unzip_malware/notoken887-1.26.37/notoken887-1.26.37/notoken887-1.26.37/notoken887/__init__.py",
      "relative_path": "notoken887-1.26.37/notoken887-1.26.37/notoken887/__init__.py",
      "is_malicious": false,
      "malicious_behavior": ""
    },
    {
      "file_path": "/home2/wenbo/Documents/PyPIAgent/Dataset/latest/unzip_malware/notoken887-1.26.37/notoken887-1.26.37/notoken887-1.26.37/notoken887/encryptor.py",
      "relative_path": "notoken887-1.26.37/notoken887-1.26.37/notoken887/encryptor.py",
      "is_malicious": false,
      "malicious_behavior": ""
    },
    {
      "file_path": "/home2/wenbo/Documents/PyPIAgent/Dataset/latest/unzip_malware/notoken887-1.26.37/notoken887-1.26.37/notoken887-1.26.37/notoken887/main.py",
      "relative_path": "notoken887-1.26.37/notoken887-1.26.37/notoken887/main.py",
      "is_malicious": true,
      "malicious_behavior": "The script has potential malicious behavior due to the use of dynamic code execution via exec, the use of a custom encryption module without clear justification, and the possibility of being used as a vector for delivering payloads. These characteristics are often associated with malware."
    }
  ],
  "true_label": "malware"
}