{
  "package_name": "pydmr",
  "is_malicious": false,
  "files_analyzed": 3,
  "malicious_files": 0,
  "file_results": [
    {
      "file_path": "/home2/wenbo/Documents/PyPIAgent/Dataset/latest/unzip_benign/pydmr/pydmr-0.0.0/src/pydmr/__init__.py",
      "relative_path": "pydmr-0.0.0/src/pydmr/__init__.py",
      "is_malicious": false,
      "malicious_behavior": ""
    },
    {
      "file_path": "/home2/wenbo/Documents/PyPIAgent/Dataset/latest/unzip_benign/pydmr/pydmr-0.0.0/src/pydmr/rw.py",
      "relative_path": "pydmr-0.0.0/src/pydmr/rw.py",
      "is_malicious": false,
      "malicious_behavior": ""
    },
    {
      "file_path": "/home2/wenbo/Documents/PyPIAgent/Dataset/latest/unzip_benign/pydmr/pydmr-0.0.0/tests/test_rw.py",
      "relative_path": "pydmr-0.0.0/tests/test_rw.py",
      "is_malicious": false,
      "malicious_behavior": ""
    }
  ],
  "true_label": "benign"
}