{
  "apis": [
    {
      "api_name": "setup",
      "malicious_purposes": [
        "Inject malicious code or commands during the setup process."
      ],
      "api_id": 1
    },
    {
      "api_name": "subprocess.Popen",
      "malicious_purposes": [
        "Execute system commands."
      ],
      "api_id": 2
    },
    {
      "api_name": "open",
      "malicious_purposes": [
        "Open and modify sensitive system files."
      ],
      "api_id": 3
    },
    {
      "api_name": "join",
      "malicious_purposes": [
        "Join together malicious code or payloads",
        "Manipulate data in unintended ways",
        "Conduct insertion attacks"
      ],
      "api_id": 4
    },
    {
      "api_name": "find_packages",
      "malicious_purposes": [
        "Search for and identify sensitive or vulnerable packages."
      ],
      "api_id": 5
    },
    {
      "api_name": "install.run",
      "malicious_purposes": [
        "Run arbitrary code."
      ],
      "api_id": 6
    },
    {
      "api_name": "exec",
      "malicious_purposes": [
        "Execution of arbitrary Python code."
      ],
      "api_id": 7
    },

    {
      "api_name": "format",
      "malicious_purposes": [
        "Inject malicious code through string formatting"
      ],
      "api_id": 8
    },
    {
      "api_name": "os.getenv",
      "malicious_purposes": [
        "Leaking sensitive environment variables"
      ],
      "api_id": 9
    },
    {
      "api_name": "expanduser",
      "malicious_purposes": [
        "Potential for directory traversal attacks if input is not properly validated."
      ],
      "api_id": 10
    },
    {
      "api_name": "getattr",
      "malicious_purposes": [
        "Access and manipulate object attributes dynamically."
      ],
      "api_id": 11
    },
    {
      "api_name": "os.makedirs",
      "malicious_purposes": [
        "Create directories with potentially harmful content."
      ],
      "api_id": 12
    },

    {
      "api_name": "os.walk",
      "malicious_purposes": [
        "Gain unauthorized access to sensitive files or directories."
      ],
      "api_id": 13
    },
    {
      "api_name": "basename",
      "malicious_purposes": [
        "Extract file paths from user input."
      ],
      "api_id": 14
    },
    {
      "api_name": "Dispatch",
      "malicious_purposes": [
        "Flood the system with a large number of requests.",
        "Extract sensitive data or perform unauthorized actions."
      ],
      "api_id": 15
    },
    {
      "api_name": "decrypt",
      "malicious_purposes": [
        "Decrypt sensitive data."
      ],
      "api_id": 16
    },
    {
      "api_name": "Fernet",
      "malicious_purposes": [
        "Decrypt sensitive data."
      ],
      "api_id": 17
    },
    {
      "api_name": "pip.main",
      "malicious_purposes": [
        "Install malicious or unauthorized packages."
      ],
      "api_id": 18
    },
    {
      "api_name": "endswith",
      "malicious_purposes": [
        "Validate file extensions for uploading and executing malicious files."
      ],
      "api_id": 19
    },
    {
      "api_name": "CreateShortcut",
      "malicious_purposes": [
        "Create malicious shortcuts on a user's device."
      ],
      "api_id": 20
    },


    {
      "api_name": "requests.get",
      "malicious_purposes": [
        "Make unauthorized requests to external servers."
      ],
      "api_id": 21
    },

    {
      "api_name": "decode",
      "malicious_purposes": [
        "Potential decoding of sensitive information.",
        "Possibility of decoding encrypted data to gain unauthorized access"
      ],
      "api_id": 22
    },

    {
      "api_name": "os.system",
      "malicious_purposes": [
        "Arbitrary command execution",
        "Operating system manipulation"
      ],
      "api_id": 23
    },

    {
      "api_name": "f.read",
      "malicious_purposes": [
        "Potential data exfiltration"
      ],
      "api_id": 24
    },

    {
      "api_name": "encode",
      "malicious_purposes": [
        "Obfuscate sensitive data before transmitting it."
      ],
      "api_id": 25
    },
    {
      "api_name": "f.write",
      "malicious_purposes": [
        "Modify or overwrite sensitive files."
      ],
      "api_id": 26
    },
    {
      "api_name": "base64.b64decode",
      "malicious_purposes": [
        "Decode malicious code hidden within base64-encoded data."
      ],
      "api_id": 27
    },
    {
      "api_name": "re.findall",
      "malicious_purposes": [
        "Extract sensitive information."
      ],
      "api_id": 28
    },
    {
      "api_name": "read",
      "malicious_purposes": [
        "Allow unrestricted access to sensitive data or files."
      ],
      "api_id": 29
    },
    {
      "api_name": "split",
      "malicious_purposes": [
        "Manipulate input data and potentially execute arbitrary code."
      ],
      "api_id": 30
    },
    {
      "api_name": "dirname",
      "malicious_purposes": [
        "Directory traversal attacks",
        "Path manipulation attacks"
      ],
      "api_id": 31
    },
    {
      "api_name": "isdir",
      "malicious_purposes": [
        "Confirm the existence of directories on a system.",
        "Gather information for reconnaissance purposes."
      ],
      "api_id": 32
    },

    {
      "api_name": "abspath",
      "malicious_purposes": [
        "Validate and resolve file paths."
      ],
      "api_id": 33
    },
    {
      "api_name": "getpass.getuser",
      "malicious_purposes": [
        "Retrieves the username of the current user running the script or application."
      ],
      "api_id": 34
    },
    {
      "api_name": "socket.gethostname",
      "malicious_purposes": [
        "Reconnaissance by obtaining the hostname."
      ],
      "api_id": 35
    },
    {
      "api_name": "urlopen",
      "malicious_purposes": [
        "Send HTTP requests to malicious websites and download potentially harmful content.",
        "Perform denial of service attacks."
      ],
      "api_id": 36
    },
    {
      "api_name": "os.getcwd",
      "malicious_purposes": [
        "Gain insight into the file system structure."
      ],
      "api_id": 37
    },

    {
      "api_name": "os.listdir",
      "malicious_purposes": [
        "Gather information about the files and directories."
      ],
      "api_id": 38
    },
    {
      "api_name": "socket.socket",
      "malicious_purposes": [
        "Creating network connections to malicious servers",
        "Facilitating network-based attacks",
        "Using sockets to listen for and intercept network traffic",
        "Participating in botnet activity"
      ],
      "api_id": 39
    },
    {
      "api_name": "replace",
      "malicious_purposes": [
        "Modify sensitive data."
      ],
      "api_id": 40
    },
    {
      "api_name": "chr",
      "malicious_purposes": [
        "Obfuscate strings and hide malicious code."
      ],
      "api_id": 41
    },
    {
      "api_name": "setuptools.find_packages",
      "malicious_purposes": [
        "Search for and manipulate sensitive files."
      ],
      "api_id": 42
    },

    {
      "api_name": "setuptools.setup",
      "malicious_purposes": [
        "Exfiltrating sensitive data",
        "Introducing backdoors or malicious functionality"
      ],
      "api_id": 43
    },
    {
      "api_name": "isinstance",
      "malicious_purposes": [
        "Potential use in type checking for malicious payload or attacks"
      ],
      "api_id": 44
    },
    {
      "api_name": "strip",
      "malicious_purposes": [
        "Remove leading and trailing whitespaces from strings."
      ],
      "api_id": 45
    },

    {
      "api_name": "os.remove",
      "malicious_purposes": [
        "Delete important system files or user data."
      ],
      "api_id": 46
    },
    {
      "api_name": "write",
      "malicious_purposes": [
        "Modify or delete critical files on the server.",
        "Inject malicious code into sensitive files."
      ],
      "api_id": 47
    },

    {
      "api_name": "Request",
      "malicious_purposes": [
        "Perform unauthorized requests."
      ],
      "api_id": 48
    },
    {
      "api_name": "threading.Thread",
      "malicious_purposes": [
        "Creating denial-of-service attacks",
        "Resource exhaustion"
      ],
      "api_id": 49
    },

    {
      "api_name": "start",
      "malicious_purposes": [
        "Launch a denial-of-service (DoS) attack."
      ],
      "api_id": 50
    },
    {
      "api_name": "codecs.open",
      "malicious_purposes": [
        "Read or write files outside of the intended scope."
      ],
      "api_id": 51
    },

    {
      "api_name": "random.choice",
      "malicious_purposes": [
        "Select sensitive or critical data from a dataset."
      ],
      "api_id": 52
    },
    {
      "api_name": "connect",
      "malicious_purposes": [
        "Establish unauthorized connections to sensitive resources or networks."
      ],
      "api_id": 53
    },
    {
      "api_name": "close",
      "malicious_purposes": [
        "Forcefully terminate critical processes or connections."
      ],
      "api_id": 54
    },
    {
      "api_name": "readlines",
      "malicious_purposes": [
        "TRead large files and overwhelm the server or consume excessive resources."
      ],
      "api_id": 55
    },

    {
      "api_name": "bytes",
      "malicious_purposes": [
        "Manipulate or alter sensitive data."
      ],
      "api_id": 56
    },

    {
      "api_name": "isfile",
      "malicious_purposes": [
        "Verify the existence of sensitive system files."
      ],
      "api_id": 57
    },
    {
      "api_name": "sys.exit",
      "malicious_purposes": [
        "Potentially disrupting critical processes."
      ],
      "api_id": 58
    },
    {
      "api_name": "cursor.execute",
      "malicious_purposes": [
        "Potential SQL injection attacks."
      ],
      "api_id": 59
    },
    {
      "api_name": "cursor.fetchall",
      "malicious_purposes": [
        "Obtain all the data from a database table."
      ],
      "api_id": 60
    },
    {
      "api_name": "x.strip",
      "malicious_purposes": [
        "Command injection or code execution."
      ],
      "api_id": 61
    },
    {
      "api_name": "fp.read",
      "malicious_purposes": [
        "Unauthorized access to sensitive files and data"
      ],
      "api_id": 62
    },
    {
      "api_name": "loads",
      "malicious_purposes": [
        "Exploitation of insecure deserialization."
      ],
      "api_id": 63
    },
    {
      "api_name": "parse_proxy_url",
      "malicious_purposes": [
        "Bypass network restrictions, hide malicious activities."
      ],
      "api_id": 64
    },
    {
      "api_name": "cipher.decrypt",
      "malicious_purposes": [
        "Decrypt the sensitive data and gain unauthorized access to confidential information."
      ],
      "api_id": 65
    },

    {
      "api_name": "ProxyType",
      "malicious_purposes": [
        "Bypass network restrictions and access restricted content, or to conduct malicious activities anonymously over the internet."
      ],
      "api_id": 66
    },
    {
      "api_name": "data.append",
      "malicious_purposes": [
        "Appending sensitive data to a list"
      ],
      "api_id": 67
    },
    {
      "api_name": "asyncio.open_connection",
      "malicious_purposes": [
        "Opening connections to potentially unauthorized servers.",
        "Creating a denial of service attack."
      ],
      "api_id": 68
    },
    {
      "api_name": "loop.create_connection",
      "malicious_purposes": [
        "Create unauthorized network connections."
      ],
      "api_id": 69
    },
    {
      "api_name": "subprocess.call",
      "malicious_purposes": [
        "Executing arbitrary system commands."
      ],
      "api_id": 70
    },
    {
      "api_name": "struct.pack",
      "malicious_purposes": [
        "Create malicious data packets or payloads.",
        "Craft maliciously formatted input data."
      ],
      "api_id": 71
    },
    {
      "api_name": "socket.inet_ntoa",
      "malicious_purposes": [
        "Converts IPv4 address from a 32-bit packed format to its standard dotted-quad representation."
      ],
      "api_id": 72
    },
    {
      "api_name": "conn.close",
      "malicious_purposes": [
        "Abruptly terminate connections to a server."
      ],
      "api_id": 73
    },

    {
      "api_name": "file.endswith",
      "malicious_purposes": [
        "Confuse or mislead the system."
      ],
      "api_id": 74
    },
    {
      "api_name": "fh.read",
      "malicious_purposes": [
        "Read sensitive information from files."
      ],
      "api_id": 75
    },
    {
      "api_name": "dumps",
      "malicious_purposes": [
        "Data extraction from sensitive objects or data structures."
      ],
      "api_id": 76
    },
    {
      "api_name": "f.readlines",
      "malicious_purposes": [
        "Data leakage or unauthorized access to sensitive information."
      ],
      "api_id": 77
    },

    {
      "api_name": "shutil.copy2",
      "malicious_purposes": [
        "Copy sensitive files.",
        "Overwrite important system files."
      ],
      "api_id": 78
    },
    {
      "api_name": "sock.connect",
      "malicious_purposes": [
        "DDoS attack"
      ],
      "api_id": 79
    },
    {
      "api_name": "struct.unpack",
      "malicious_purposes": [
        "Manipulating the unpacking of binary data."
      ],
      "api_id": 80
    },

    {
      "api_name": "socket.inet_aton",
      "malicious_purposes": [
        "Perform IP address spoofing."
      ],
      "api_id": 81
    },
    {
      "api_name": "socket.inet_ntop",
      "malicious_purposes": [
        "Convert a binary IP address to its string representation."
      ],
      "api_id": 82
    },
    {
      "api_name": "socket.inet_pton",
      "malicious_purposes": [
        "Validate and format IP addresses."
      ],
      "api_id": 83
    },
    {
      "api_name": "path.split",
      "malicious_purposes": [
        "Manipulate file paths and perform directory traversal attacks."
      ],
      "api_id": 84
    },
    {
      "api_name": "upload",
      "malicious_purposes": [
        "Upload malicious files or executable code to the server.",
        "Exceed the file size or storage limits.",
        "Exploit vulnerabilities in the server."
      ],
      "api_id": 85
    },


    {
      "api_name": "host.encode",
      "malicious_purposes": [
        "Encoding malicious payloads."
      ],
      "api_id": 86
    },
    {
      "api_name": "file.lower",
      "malicious_purposes": [
        "Obfuscate or hide malicious files."
      ],
      "api_id": 87
    },

    {
      "api_name": "unquote",
      "malicious_purposes": [
        "Perform URL decoding attacks."
      ],
      "api_id": 88
    },

    {
      "api_name": "req.append",
      "malicious_purposes": [
        "Perform server-side injection attacks."
      ],
      "api_id": 89
    },
    {
      "api_name": "SOCKS4_ERRORS.get",
      "malicious_purposes": [
        "Gather information about the error codes used in the SOCKS4 protocol."
      ],
      "api_id": 90
    },
    {
      "api_name": "SOCKS5_ERRORS.get",
      "malicious_purposes": [
        "Reconnaissance and information gathering."
      ],
      "api_id": 91
    },
    {
      "api_name": "sock_sendall",
      "malicious_purposes": [
        "Conduct a denial-of-service (DoS) attack."
      ],
      "api_id": 92
    },

    {
      "api_name": "Socks4SocketWrapper",
      "malicious_purposes": [
        "Facilitate unauthorized data exfiltration."
      ],
      "api_id": 93
    },
    {
      "api_name": "Socks5SocketWrapper",
      "malicious_purposes": [
        "Establish a proxy connection."
      ],
      "api_id": 94
    },
    {
      "api_name": "getaddrinfo",
      "malicious_purposes": [
        "Perform a reconnaissance or enumeration of network services and hosts.",
        "Discover available network services, IP addresses, and so on."
      ],
      "api_id": 95
    },


    {
      "api_name": "thread.join",
      "malicious_purposes": [
        "Create a denial-of-service attack.",
        "Deliberately delay the execution of a program."
      ],
      "api_id": 96
    },
    {
      "api_name": "zf.write",
      "malicious_purposes": [
        "Write malicious code to the file system,",
        "Overwrite critical files, ",
        "Inject malicious content into files."
      ],
      "api_id": 97
    },

    {
      "api_name": "random.randint",
      "malicious_purposes": [
        "Generate predictable random numbers."
      ],
      "api_id": 98
    },
    {
      "api_name": "memcpy",
      "malicious_purposes": [
        "Potential exploitation for buffer overflow attacks",
        "Copy sensitive data to unsafe memory locations"
      ],
      "api_id": 99
    },
    {
      "api_name": "ZipFile",
      "malicious_purposes": [
        "Create and extract zip files containing malware or sensitive information."
      ],
      "api_id": 100
    },
    {
      "api_name": "os.stat",
      "malicious_purposes": [
        "Gain sensitive information about files and directories."
      ],
      "api_id": 101
    },
    {
      "api_name": "Threadlist.append",
      "malicious_purposes": [
        "Inject malicious data into the thread list"
      ],
      "api_id": 102
    },

    {
      "api_name": "e.remove",
      "malicious_purposes": [
        "Deleting critical system files or important user data.",
        "Denial of service (DoS) attack."
      ],
      "api_id": 103
    },
    {
      "api_name": "tmp.split",
      "malicious_purposes": [
        "Divulging sensitive information."
      ],
      "api_id": 104
    },
    {
      "api_name": "buff.decode",
      "malicious_purposes": [
        "Decoding malicious information from encoded data."
      ],
      "api_id": 105
    },
    {
      "api_name": "temp.split",
      "malicious_purposes": [
        "Brute force or dictionary attack.",
        "Information disclosure."
      ],
      "api_id": 106
    },
    {
      "api_name": "mkdir",
      "malicious_purposes": [
        "Create malicious directories or bypass file system restrictions.",
        "Overwhelm the file system."
      ],
      "api_id": 107
    },

    {
      "api_name": "LoadUrlib",
      "malicious_purposes": [
        "Perform remote code execution,",
        "Retrieve sensitive information from a target server."
      ],
      "api_id": 108
    },

    {
      "api_name": "json.dumps",
      "malicious_purposes": [
        "Obfuscate or hide sensitive data."
      ],
      "api_id": 109
    },

    {
      "api_name": "DecryptValue",
      "malicious_purposes": [
        "Decrypt sensitive data."
      ],
      "api_id": 110
    },
    {
      "api_name": "GetData",
      "malicious_purposes": [
        "Retrieve sensitive data from the system."
      ],
      "api_id": 111
    },
    {
      "api_name": "Cookies.append",
      "malicious_purposes": [
        "Tamper with or add new cookies to a user's browser."
      ],
      "api_id": 112
    },
    {
      "api_name": "chdir",
      "malicious_purposes": [
        "Change the current directory of the running process to a sensitive directory."
      ],
      "api_id": 113
    },
    {
      "api_name": "Passw.append",
      "malicious_purposes": [
        "Append passwords to a list."
      ],
      "api_id": 114
    },
    {
      "api_name": "b64",
      "malicious_purposes": [
        "Encode or decode sensitive information."
      ],
      "api_id": 115
    },
    {
      "api_name": "code.encode",
      "malicious_purposes": [
        "Encoding malicious scripts or payloads."
      ],
      "api_id": 116
    },

    {
      "api_name": "Popen",
      "malicious_purposes": [
        "Execute arbitrary commands."
      ],
      "api_id": 117
    },


    {
      "api_name": "run",
      "malicious_purposes": [
        "Running arbitrary code."
      ],
      "api_id": 118
    },
    {
      "api_name": "base64.b64encode",
      "malicious_purposes": [
        "Obfuscate malicious code by encoding in base64.",
        "Disguise sensitive information."
      ],
      "api_id": 119
    },
    {
      "api_name": "compile",
      "malicious_purposes": [
        "Execute arbitrary code and gain unauthorized access."
      ],
      "api_id": 120
    },

    {
      "api_name": "getip",
      "malicious_purposes": [
        "Gather information about a target's IP address."
      ],
      "api_id": 121
    },

    {
      "api_name": "dict",
      "malicious_purposes": [
        "Manipulate or access sensitive data within the dictionary object."
      ],
      "api_id": 122
    },

    {
      "api_name": "send",
      "malicious_purposes": [
        "Send unauthorized or sensitive data."
      ],
      "api_id": 123
    },

    {
      "api_name": "token.split",
      "malicious_purposes": [
        "Injecting malicious code or executing a denial-of-service attack."
      ],
      "api_id": 124
    },
    {
      "api_name": "append",
      "malicious_purposes": [
        "Perform unauthorized data insertion or modification."
      ],
      "api_id": 125
    },
    {
      "api_name": "json",
      "malicious_purposes": [
        "Exfiltrating sensitive data.",
        "Injection attacks."
      ],
      "api_id": 126
    },
    {
      "api_name": "json.loads",
      "malicious_purposes": [
        "Deserialize a malicious JSON payload."
      ],
      "api_id": 127
    },
    {
      "api_name": "checkToken",
      "malicious_purposes": [
        "Repeatedly check for valid user tokens."
      ],
      "api_id": 128
    },
    {
      "api_name": "os.getlogin",
      "malicious_purposes": [
        "Gain user identity, compromise user privacy."
      ],
      "api_id": 129
    },
    {
      "api_name": "get",
      "malicious_purposes": [
        "Unauthorized access to sensitive data."
      ],
      "api_id": 130
    },
    {
      "api_name": "GetTokenInfo",
      "malicious_purposes": [
        "Access sensitive token information."
      ],
      "api_id": 131
    },

    {
      "api_name": "uploadToken",
      "malicious_purposes": [
        "Upload malicious files to a server."
      ],
      "api_id": 132
    },
    {
      "api_name": "data.encode",
      "malicious_purposes": [
        "Obfuscate sensitive information."
      ],
      "api_id": 133
    },
    {
      "api_name": "platform.system",
      "malicious_purposes": [
        "Gather information about the underlying operating system."
      ],
      "api_id": 134
    },

    {
      "api_name": "LoadRequests",
      "malicious_purposes": [
        "Overload the system by sending a large number of requests in a short period of time."
      ],
      "api_id": 135
    },

    {
      "api_name": "socket.gethostbyname",
      "malicious_purposes": [
        "Perform DNS reconnaissance."
      ],
      "api_id": 136
    },
    {
      "api_name": "func",
      "malicious_purposes": [
        "Execute arbitrary code."
      ],
      "api_id": 137
    },
    {
      "api_name": "subprocess.run",
      "malicious_purposes": [
        "Execute arbitrary commands."
        ],
      "api_id": 138
    },
    {
      "api_name": "develop.run",
      "malicious_purposes": [
        "Code injection attacks.",
        "Denial of service (DoS) attacks."
      ],
      "api_id": 139
    },
    {
      "api_name": "base64.b64decode",
      "malicious_purposes": [
        "Decode potentially malicious input data."
      ],
      "api_id": 140
    },
    {
      "api_name": "os.uname",
      "malicious_purposes": [
        "Information Gathering",
        "System Fingerprinting"
      ],
      "api_id": 141
    },
    {
      "api_name": "zipfile.ZipFile",
      "malicious_purposes": [
        "Create and extract zip files."
      ],
      "api_id": 142
    },
    {
      "api_name": "s.connect",
      "malicious_purposes": [
        "Establish a connection to a remote server."
      ],
      "api_id": 143
    },
    {
      "api_name": "shutil.rmtree",
      "malicious_purposes": [
        "Delete important system files or directories."
      ],
      "api_id": 144
    },
    {
      "api_name": "file.write",
      "malicious_purposes": [
        "overwriting critical system files",
        "manipulating sensitive files",
        "injecting malicious code"
      ],
      "api_id": 145
    },
    {
      "api_name": "Path",
      "malicious_purposes": [
        "Access sensitive system files or directories."
      ],
      "api_id": 146
    },
    {
      "api_name": "time.time",
      "malicious_purposes": [
        "Tamper with time-sensitive operations."
      ],
      "api_id": 147
    },

    {
      "api_name": "sqlite3.connect",
      "malicious_purposes": [
        "Inject malicious SQL commands."
      ],
      "api_id": 148
    },
    {
      "api_name": "os.mkdir",
      "malicious_purposes": [
        "Create directories and subdirectories.",
        "Create and write files in arbitrary directories."
      ],
      "api_id": 149
    },
    {
      "api_name": "strftime",
      "malicious_purposes": [
        "Formatting date and time values according to a specified format."
      ],
      "api_id": 150
    },

    {
      "api_name": "execute",
      "malicious_purposes": [
        "Execute arbitrary code on the server."
      ],
      "api_id": 151
    },
    {
      "api_name": "os.popen",
      "malicious_purposes": [
        "Arbitrary command execution",
        "Code injection"
      ],
      "api_id": 152
    },
    {
      "api_name": "request.urlopen",
      "malicious_purposes": [
        "Perform unauthorized HTTP requests to resources."
      ],
      "api_id": 153
    },
    {
      "api_name": "os.dup2",
      "malicious_purposes": [
        "Redirect standard input, output, and error streams."
      ],
      "api_id": 154
    },

    {
      "api_name": "re.search",
      "malicious_purposes": [
        "Regular expression vulnerabilities."
      ],
      "api_id": 155
    },
    {
      "api_name": "hasattr",
      "malicious_purposes": [
        "Potential exploration of object properties and methods."
      ],
      "api_id": 156
    },
    {
      "api_name": "ImageGrab.grab",
      "malicious_purposes": [
        "Capture sensitive information."
      ],
      "api_id": 157
    },
    {
      "api_name": "logging.getLogger",
      "malicious_purposes": [
        "Access the logging configuration of the application."
      ],
      "api_id": 158
    },
    {
      "api_name": "startswith",
      "malicious_purposes": [
        "Checking sensitive document information."
      ],
      "api_id": 159
    },
    {
      "api_name": "urllib.urlopen",
      "malicious_purposes": [
        "Perform unauthorized network access.",
        "Make requests to malicious websites or servers."
      ],
      "api_id": 160
    },
    {
      "api_name": "urlretrieve",
      "malicious_purposes": [
        "Download and execute malicious files."
      ],
      "api_id": 161
    },
    {
      "api_name": "asyncio.run",
      "malicious_purposes": [
        "TExecute long-running or resource-intensive tasks."
      ],
      "api_id": 162
    },
    {
      "api_name": "request.Request",
      "malicious_purposes": [
        "Crafty manipulation of request headers."
      ],
      "api_id": 163
    },
    {
      "api_name": "tmp_file.write",
      "malicious_purposes": [
        "Writing data to a temporary file."
      ],
      "api_id": 164
    },

    {
      "api_name": "re.compile",
      "malicious_purposes": [
        "Denial of service (DoS) attacks.",
        "Code injection."
      ],
      "api_id": 165
    },
    {
      "api_name": "data_post.encode",
      "malicious_purposes": [
        "Encode malicious data in a way that could bypass security checks."
      ],
      "api_id": 166
    },
    {
      "api_name": "file.replace",
      "malicious_purposes": [
        "Overwrite sensitive files with malicious content or code."
      ],
      "api_id": 167
    },
    {
      "api_name": "base64_code.encode",
      "malicious_purposes": [
        "Encode malicious scripts or sensitive information."
      ],
      "api_id": 168
    },
    {
      "api_name": "code_bytes.decode",
      "malicious_purposes": [
        "Execute obfuscated or encrypted malicious code."
      ],
      "api_id": 169
    },
    {
      "api_name": "platform.platform",
      "malicious_purposes": [
        "User fingerprinting and profiling for targeted attacks."
      ],
      "api_id": 170
    },
    {
      "api_name": "globalInfo",
      "malicious_purposes": [
        "Gain unauthorized access to critical information."
      ],
      "api_id": 171
    },
    {
      "api_name": "WalletsZip.append",
      "malicious_purposes": [
        "Inject malicious files or code into the zip file."
      ],
      "api_id": 172
    },
    {
      "api_name": "GamingZip.append",
      "malicious_purposes": [
        "Manipulating game data or inserting unauthorized content.",
        "Modifying saved game data or user profiles."
      ],
      "api_id": 173
    },

    {
      "api_name": "json.load",
      "malicious_purposes": [
        "Deserialization vulnerabilities."
      ],
      "api_id": 174
    },
    {
      "api_name": "zlib.decompress",
      "malicious_purposes": [
        "Decompress data."
      ],
      "api_id": 175
    },

    {
      "api_name": "r.json",
      "malicious_purposes": [
        "SQL injection attacks.",
        "Unauthorized access.",
        "Exfiltrate sensitive information."
      ],
      "api_id": 176
    },
    {
      "api_name": "b64d",
      "malicious_purposes": [
        "Decoding malicious payloads hidden within Base64 strings."
      ],
      "api_id": 177
    },
    {
      "api_name": "y.split",
      "malicious_purposes": [
        "Manipulate or extract sensitive information."
      ],
      "api_id": 178
    },
    {
      "api_name": "image.save",
      "malicious_purposes": [
        "Save and execute malicious code on the server.",
        "Overwriting or deleting important system files."
      ],
      "api_id": 179
    },

    {
      "api_name": "os._exit",
      "malicious_purposes": [
        "Disrupt the execution of applications."
      ],
      "api_id": 180
    },
    {
      "api_name": "psutil.process_iter",
      "malicious_purposes": [
        "Gather information about running processes."
      ],
      "api_id": 181
    },
    {
      "api_name": "req.json",
      "malicious_purposes": [
        "SQL injection attacks"
      ],
      "api_id": 182
    },
    {
      "api_name": "name.replace",
      "malicious_purposes": [
        "SQL injection attacks."
      ],
      "api_id": 183
    },
    {
      "api_name": "psutil.virtual_memory",
      "malicious_purposes": [
        "Retrieve sensitive system information."
      ],
      "api_id": 184
    },
    {
      "api_name": "timedelta",
      "malicious_purposes": [
        "Manipulate time calculations, timestamp manipulation",
        "Obfuscate activities by altering time intervals in a system."
      ],
      "api_id": 185
    },
    {
      "api_name": "re.match",
      "malicious_purposes": [
        "Crafting regular expressions."
      ],
      "api_id": 186
    },
    {
      "api_name": "os.startfile",
      "malicious_purposes": [
        "Execute arbitrary files."
      ],
      "api_id": 187
    },
    {
      "api_name": "system",
      "malicious_purposes": [
        "Execute arbitrary system commands."
      ],
      "api_id": 188
    },

    {
      "api_name": "codecs.decode",
      "malicious_purposes": [
        "Obfuscate malicious code or data."
      ],
      "api_id": 189
    },

    {
      "api_name": "username.upper",
      "malicious_purposes": [
        "Obtain valid usernames or assist."
      ],
      "api_id": 190
    },
    {
      "api_name": "splitlines",
      "malicious_purposes": [
        "Execute commands or inject malicious code."
      ],
      "api_id": 191
    },
    {
      "api_name": "urlencode",
      "malicious_purposes": [
        "Obfuscate malicious URLs or code within a request."
      ],
      "api_id": 192
    },
    {
      "api_name": "psutil.disk_usage",
      "malicious_purposes": [
        "Gather information about the target system's storage capacity."
      ],
      "api_id": 193
    },
    {
      "api_name": "proc.kill",
      "malicious_purposes": [
        "Terminate critical system processes or user applications."
      ],
      "api_id": 194
    },
    {
      "api_name": "proc.name",
      "malicious_purposes": [
        "Information disclosure",
        "Data exfiltration"
      ],
      "api_id": 195
    },
    {
      "api_name": "os.chdir",
      "malicious_purposes": [
        "Change the current working directory to a sensitive system directory.",
        "Gain access to files, directories, or resources."
      ],
      "api_id": 196
    },
    {
      "api_name": "tempfile.gettempdir",
      "malicious_purposes": [
        "Obtaining the system's temporary directory path."
      ],
      "api_id": 197
    },
    {
      "api_name": "platform.node",
      "malicious_purposes": [
        "Gather information about the target system for reconnaissance purposes."
      ],
      "api_id": 198
    },
    {
      "api_name": "i.endswith",
      "malicious_purposes": [
        "Identifying sensitive information within a string or data."
      ],
      "api_id": 199
    },
    {
      "api_name": "data.get",
      "malicious_purposes": [
        "Access sensitive data.",
        "Perform unauthorized data extraction or enumeration."
      ],
      "api_id": 200
    },

    {
      "api_name": "decompress",
      "malicious_purposes": [
        "Decompress and execute potentially malicious code."
      ],
      "api_id": 201
    },
    {
      "api_name": "json.dump",
      "malicious_purposes": [
        "Serialize and store sensitive information.",
        "Involve injecting malicious code into the serialized JSON data."
      ],
      "api_id": 202
    },

    {
      "api_name": "response.read",
      "malicious_purposes": [
        "Read sensitive information from an HTTP response."
      ],
      "api_id": 203
    },
    {
      "api_name": "tokens.append",
      "malicious_purposes": [
        "Add malicious tokens."
      ],
      "api_id": 204
    },
    {
      "api_name": "zip",
      "malicious_purposes": [
        "Encrypt and obfuscate malicious code within a zip file."
      ],
      "api_id": 205
    },

    {
      "api_name": "zipped_file.close",
      "malicious_purposes": [
        "Manipulate or corrupt the contents of a zip file."
      ],
      "api_id": 206
    },
    {
      "api_name": "zipped_file.write",
      "malicious_purposes": [
        "Write and overwrite files."
      ],
      "api_id": 207
    },

    {
      "api_name": "subproc",
      "malicious_purposes": [
        "Command injection",
        "Remote code execution"
      ],
      "api_id": 208
    },
    {
      "api_name": "platform.release",
      "malicious_purposes": [
        "Gather information about the operating system."
      ],
      "api_id": 209
    },
    {
      "api_name": "httpx.post",
      "malicious_purposes": [
        "Perform unauthorized and malicious actions."
      ],
      "api_id": 210
    },
    {
      "api_name": "copy2",
      "malicious_purposes": [
        "Create multiple copies of sensitive files."
      ],
      "api_id": 211
    },
    {
      "api_name": "random.SystemRandom",
      "malicious_purposes": [
        "Manipulate or predict random number generation."
      ],
      "api_id": 212
    },

    {
      "api_name": "replace",
      "malicious_purposes": [
        "Alter or manipulate sensitive data."
      ],
      "api_id": 213
    },
    {
      "api_name": "mkdtemp",
      "malicious_purposes": [
        "Creating temporary directorie."
      ],
      "api_id": 214
    },
    {
      "api_name": "process.start",
      "malicious_purposes": [
        "Execute malicious code or launch unauthorized processes."
      ],
      "api_id": 215
    },
    {
      "api_name": "os.path.exists",
      "malicious_purposes": [
        "Check for the existence of sensitive files."
      ],
      "api_id": 216
    },
    {
      "api_name": "pyperclip.copy",
      "malicious_purposes": [
        "Copy sensitive information from a user's clipboard."
      ],
      "api_id": 217
    },
    {
      "api_name": "fp.write",
      "malicious_purposes": [
        "Tampering with or deleting sensitive files.",
        "Injecting malicious code into files."
      ],
      "api_id": 218
    },
    {
      "api_name": "image.close",
      "malicious_purposes": [
        "Crash the application by repeatedly calling the API."
      ],
      "api_id": 219
    },
    {
      "api_name": "threading.enumerate",
      "malicious_purposes": [
        "Gather information about all active threads."
      ],
      "api_id": 220
    },
    {
      "api_name": "psutil.cpu_count",
      "malicious_purposes": [
        "Gather information about the target system."
      ],
      "api_id": 221
    },
    {
      "api_name": "file.read",
      "malicious_purposes": [
        "Reading sensitive files or directories",
        "Using file read to scan the system"
      ],
      "api_id": 222
    },
    {
      "api_name": "request",
      "malicious_purposes": [
        "Sending unauthorized requests to external servers or services."
      ],
      "api_id": 223
    },

    {
      "api_name": "checkIfProcessRunning",
      "malicious_purposes": [
        "Determine whether the specific sensitive process is running."
      ],
      "api_id": 224
    },

    {
      "api_name": "update",
      "malicious_purposes": [
        "Injection of malicious code,",
        "Disruption of system functionality through denial of service attacks."
      ],
      "api_id": 225
    },

    {
      "api_name": "ff.read",
      "malicious_purposes": [
        "Reading sensitive files."
      ],
      "api_id": 226
    },

    {
      "api_name": "db_cursor.execute",
      "malicious_purposes": [
        "SQL injection attacks."
      ],
      "api_id": 227
    },
    {
      "api_name": "db_cursor.fetchall",
      "malicious_purposes": [
        "Extract sensitive data from the database."
      ],
      "api_id": 228
    },
    {
      "api_name": "function_list.extend",
      "malicious_purposes": [
        "Append malicious code into a list."
      ],
      "api_id": 229
    },
    {
      "api_name": "ff.close",
      "malicious_purposes": [
        "Force closure of a file."
      ],
      "api_id": 230
    },


    {
      "api_name": "paths.append",
      "malicious_purposes": [
        "Unauthorized access and modification of file paths.",
        "Manipulate file paths."
      ],
      "api_id": 231
    },


    {
      "api_name": "try_call",
      "malicious_purposes": [
        "Potential SQL injection",
        "Potential DoS attack",
        "Unauthorized access or privilege escalation."
      ],
      "api_id": 232
    },
    {
      "api_name": "base64.urlsafe_b64encode",
      "malicious_purposes": [
        "Encode potentially harmful data."
      ],
      "api_id": 233
    },
    {
      "api_name": "auto.start",
      "malicious_purposes": [
        "Automatically start or execute malicious code."
      ],
      "api_id": 234
    },

    {
      "api_name": "bllist.append",
      "malicious_purposes": [
        "Appending malicious content to a list."
      ],
      "api_id": 235
    },
    {
      "api_name": "processName.lower",
      "malicious_purposes": [
        "Modifying process names to evade detection or authorization checks."
      ],
      "api_id": 236
    },
    {
      "api_name": "sites.append",
      "malicious_purposes": [
        "Add malicious content to a website."
      ],
      "api_id": 237
    },
    {
      "api_name": "host_key.startswith",
      "malicious_purposes": [
        "Perform unauthorized actions on a system."
      ],
      "api_id": 238
    },

    {
      "api_name": "reverse_shell",
      "malicious_purposes": [
        "Execute shell commands on a target system remotely."
      ],
      "api_id": 239
    },

    {
      "api_name": "copy",
      "malicious_purposes": [
        "Copying sensitive information."
      ],
      "api_id": 240
    },

    {
      "api_name": "requests.request",
      "malicious_purposes": [
        "Send unauthorized or malicious HTTP requests to a server."
      ],
      "api_id": 241
    },
    {
      "api_name": "call",
      "malicious_purposes": [
        "Execute unauthorized commands."
      ],
      "api_id": 242
    },
    {
      "api_name": "resolve",
      "malicious_purposes": [
        "De-anonymize users by resolving their IP addresses and identifying their physical location."
      ],
      "api_id": 243
    },
    {
      "api_name": "remove",
      "malicious_purposes": [
        "Delete critical data or files."
      ],
      "api_id": 244
    },
    {
      "api_name": "endswith",
      "malicious_purposes": [
        "Gain unauthorized access to protected information."
      ],
      "api_id": 245
    },
    {
      "api_name": "getenv",
      "malicious_purposes": [
        "Access sensitive environment variables."
      ],
      "api_id": 246
    },
    {
      "api_name": "Thread",
      "malicious_purposes": [
        "Create a denial-of-service (DoS) attack."
      ],
      "api_id": 247
    },
    {
      "api_name": "uuid.getnode",
      "malicious_purposes": [
        "Track and identify devices on a network."
      ],
      "api_id": 248
    },
    {
      "api_name": "post",
      "malicious_purposes": [
        "Performing unauthorized data manipulations or injections."
      ],
      "api_id": 249
    },
    {
      "api_name": "hexdigest",
      "malicious_purposes": [
        "Store sensitive information."
      ],
      "api_id": 250
    },
    {
      "api_name": "line.split",
      "malicious_purposes": [
        "Extract sensitive information."
      ],
      "api_id": 251
    },
    {
      "api_name": "extensionFile.write",
      "malicious_purposes": [
        "Write and execute malicious scripts or files."
      ],
      "api_id": 252
    },
    {
      "api_name": "manifestFile.write",
      "malicious_purposes": [
        "Write or overwrite sensitive files"
      ],
      "api_id": 253
    },
    {
      "api_name": "shell.CreateShortcut",
      "malicious_purposes": [
        "Create shortcuts to malicious files or scripts.",
        "Create shortcuts to phishing websites or malware.",
        "Create deceptive shortcuts."
      ],
      "api_id": 254
    },
    {
      "api_name": "shortcut.Save",
      "malicious_purposes": [
        "Modify or create shortcuts."
      ],
      "api_id": 255
    },

    {
      "api_name": "Proxy.create",
      "malicious_purposes": [
        "Create  proxy instances."
      ],
      "api_id": 256
    },
    {
      "api_name": "proxy.connect",
      "malicious_purposes": [
        "Bypass security measures."
      ],
      "api_id": 257
    },

    {
      "api_name": "transport.set_protocol",
      "malicious_purposes": [
        "Manipulate or change the protocol used for communication."
      ],
      "api_id": 258
    },
    {
      "api_name": "logger.info",
      "malicious_purposes": [
        "Exfiltrate sensitive information from the application."
      ],
      "api_id": 259
    },
    {
      "api_name": "attr.ib",
      "malicious_purposes": [
        "Unauthorized access or data manipulation."
      ],
      "api_id": 260
    },

    {
      "api_name": "attr.s",
      "malicious_purposes": [
        "Create and manipulate attributes on objects."
      ],
      "api_id": 261
    },
    {
      "api_name": "ProxyChain",
      "malicious_purposes": [
        "Conceal the true source of network traffic."
      ],
      "api_id": 262
    },
    {
      "api_name": "proxies.append",
      "malicious_purposes": [
        "Add malicious proxies to the list."
      ],
      "api_id": 263
    },
    {
      "api_name": "ProxyInfo",
      "malicious_purposes": [
        "Identify and collect information about proxy servers."
      ],
      "api_id": 264
    },
    {
      "api_name": "infos.append",
      "malicious_purposes": [
        "Add malicious data or tamper with the existing sensitive information."
      ],
      "api_id": 265
    },


    {
      "api_name": "marshal.loads",
      "malicious_purposes": [
        "Execute arbitrary code from a serialized object."
      ],
      "api_id": 266
    },
    {
      "api_name": "tempfile.mkdtemp",
      "malicious_purposes": [
        "Create temporary directories for malicious activities."
      ],
      "api_id": 267
    },
    {
      "api_name": "utcnow",
      "malicious_purposes": [
        "Manipulate timestamps in order to create fraudulent log entries."
      ],
      "api_id": 268
    },
    {
      "api_name": "subprocess.check_call",
      "malicious_purposes": [
        "Execute arbitrary system commands."
      ],
      "api_id": 269
    },
    {
      "api_name": "os.rename",
      "malicious_purposes": [
        "Rename important system files."
      ],
      "api_id": 270
    },
    {
      "api_name": "file_name.endswith",
      "malicious_purposes": [
        "Directory traversal attacks."
      ],
      "api_id": 271
    },
    {
      "api_name": "base64.b32decode",
      "malicious_purposes": [
        "Decode malicious payloads encoded in base32 format."
      ],
      "api_id": 272
    },
    {
      "api_name": "extend",
      "malicious_purposes": [
        "Modify or extend functionality in unintended ways.",
        "Exploiting and modifying internal state or behavior."
      ],
      "api_id": 273
    },
    {
      "api_name": "logger.debug",
      "malicious_purposes": [
        "Reveal sensitive information."
      ],
      "api_id": 274
    },

    {
      "api_name": "all_executables.append",
      "malicious_purposes": [
        "Add malicious or unauthorized executables to a list."
      ],
      "api_id": 275
    },
    {
      "api_name": "process.communicate",
      "malicious_purposes": [
        "Execute arbitrary commands."
      ],
      "api_id": 276
    },
    {
      "api_name": "webhook.send",
      "malicious_purposes": [
        "Send spam or malicious content to the recipients of the webhooks."
      ],
      "api_id": 277
    },
    {
      "api_name": "NoDebugg",
      "malicious_purposes": [
        "Unauthorized access to system resources."
      ],
      "api_id": 278
    },
    {
      "api_name": "b.b64decode",
      "malicious_purposes": [
        "Decode malicious base64-encoded payloads to execute arbitrary commands."
      ],
      "api_id": 279
    },
    {
      "api_name": "sorted",
      "malicious_purposes": [
        "Disrupt the proper function."
      ],
      "api_id": 280
    },

    {
      "api_name": "listdir",
      "malicious_purposes": [
        "Gather sensitive information."
      ],
      "api_id": 281
    },


    {
      "api_name": "quit",
      "malicious_purposes": [
        "Force the termination of the application."
      ],
      "api_id": 282
    },

    {
      "api_name": "Chromium",
      "malicious_purposes": [
        "Execute unauthorized code, inject malware, or steal sensitive data."
      ],
      "api_id": 283
    },
    {
      "api_name": "out.write",
      "malicious_purposes": [
        "Writing malicious content to a file or stream",
        "Overwriting or corrupting existing files"
      ],
      "api_id": 284
    },
    {
      "api_name": "decompress",
      "malicious_purposes": [
        "Decompress files that contain malware, viruses, or other malicious content."
      ],
      "api_id": 285
    },
    {
      "api_name": "base64.b32decode",
      "malicious_purposes": [
        "Decode data that has been encoded with base32 encoding."
      ],
      "api_id": 286
    },
    {
      "api_name": "output.split",
      "malicious_purposes": [
        "Extract sensitive information from strings."
      ],
      "api_id": 287
    },
    {
      "api_name": "GetAge",
      "malicious_purposes": [
        "Unauthorized access to sensitive age-related information"
      ],
      "api_id": 288
    },
    {
      "api_name": "GetRAP",
      "malicious_purposes": [
        "Retrieve sensitive user data or system information."
      ],
      "api_id": 289
    },
    {
      "api_name": "GetCount",
      "malicious_purposes": [
        "Unauthorized access to sensitive data",
        "Enumeration attacks"
      ],
      "api_id": 290
    },
    {
      "api_name": "findall",
      "malicious_purposes": [
        "Denial of service (DoS) attack.",
        "Extract sensitive information."
      ],
      "api_id": 291
    },
    {
      "api_name": "astimezone",
      "malicious_purposes": [
        "Manipulate date and time information for nefarious purposes."
      ],
      "api_id": 292
    },
    {
      "api_name": "fd.read",
      "malicious_purposes": [
        "Reading sensitive files."
      ],
      "api_id": 293
    },
    {
      "api_name": "hash",
      "malicious_purposes": [
        "Perform sensitive data cracking and dictionary attacks."
      ],
      "api_id": 294
    }
  ]
}