{
  "package_name": "website-mobile-preview",
  "is_malicious": false,
  "files_analyzed": 2,
  "malicious_files": 0,
  "file_results": [
    {
      "file_path": "/home2/blue/Documents/PyPIAgent/Dataset/npm_data/unzip_benign/website-mobile-preview/biomp.js",
      "relative_path": "biomp.js",
      "file_type": "js",
      "is_malicious": false,
      "malicious_behavior": ""
    },
    {
      "file_path": "/home2/blue/Documents/PyPIAgent/Dataset/npm_data/unzip_benign/website-mobile-preview/package.json",
      "relative_path": "package.json",
      "file_type": "package.json",
      "is_malicious": false,
      "malicious_behavior": ""
    }
  ],
  "true_label": "benign"
}