{
  "metadata": {
    "package_name": "blaze-0",
    "original_json_path": "/home2/blue/Documents/PyPIAgent/Codes/code_contexral/codesnippets/benign/blaze-0.10.1.json",
    "dataset_type": "benign"
  },
  "code_files": [
    {
      "pyfile": "python.py",
      "full_path": "/home2/blue/Documents/PyPIAgent/Dataset/study/unzip_benign/blaze-0.10.1/blaze-0.10.1/blaze/compute/python.py",
      "line_number": "380",
      "type_description": "obfuscation",
      "context_snippet": "from ..compatibility import builtins, apply, unicode, _inttypes\n\n@dispatch(Reduction, Sequence)\ndef compute_up_1d(t, seq, **kwargs):\n    op = getattr(builtins, t.symbol)\n    return op(seq)",
      "hash_value": "e11f1196c6b121c7adda7c12f3d338d5",
      "detection_index": 1,
      "code_snippets": [
        {
          "snippet": "from ..compatibility import builtins, apply, unicode, _inttypes\n\n@dispatch(Reduction, Sequence)\ndef compute_up_1d(t, seq, **kwargs):\n    op = getattr(builtins, t.symbol)\n    return op(seq)",
          "triple_sequences": [
            {
              "action_api": "getattr()",
              "action_description": "Checks if object is instance of specified type",
              "action_id": "check_instance_type",
              "object": "builtins, t.symbol",
              "object_description": "Built-in module or package",
              "object_id": "builtin_module",
              "intention_description": "Access attribute value",
              "intention_id": "access_attribute_value"
            },
            {
              "action_api": "op()",
              "action_description": "Executes Python code",
              "action_id": "execute_python_code",
              "object": "seq",
              "object_description": "",
              "object_id": "",
              "intention_description": "Evaluate constructed code",
              "intention_id": "evaluate_constructed_code"
            }
          ]
        }
      ]
    }
  ]
}