{
  "metadata": {
    "package_name": "bpython-0",
    "original_json_path": "/home2/blue/Documents/PyPIAgent/Codes/code_contexral/codesnippets/benign/bpython-0.25.json",
    "dataset_type": "benign"
  },
  "code_files": [
    {
      "pyfile": "repl.py",
      "full_path": "/home2/blue/Documents/PyPIAgent/Dataset/study/unzip_benign/bpython-0.25/bpython-0.25/bpython/repl.py",
      "line_number": "936",
      "type_description": "clipboard-access",
      "context_snippet": "def copy2clipboard(self) -> None:\n    \"\"\"Copy current content to clipboard.\"\"\"\n\n    if not have_pyperclip:\n        self.interact.notify(_(\"No clipboard available.\"))\n        return\n\n    content = self.get_session_formatted_for_file()\n    try:\n        pyperclip.copy(content)\n    except pyperclip.PyperclipException:\n        self.interact.notify(_(\"Could not copy to clipboard.\"))\n    else:\n        self.interact.notify(_(\"Copied content to clipboard.\"))",
      "hash_value": "3376e57b3c056ac859a64c3bad748418",
      "detection_index": 1,
      "code_snippets": [
        {
          "snippet": "def copy2clipboard(self) -> None:\n    \"\"\"Copy current content to clipboard.\"\"\"\n\n    if not have_pyperclip:\n        self.interact.notify(_(\"No clipboard available.\"))\n        return\n\n    content = self.get_session_formatted_for_file()\n    try:\n        pyperclip.copy(content)\n    except pyperclip.PyperclipException:\n        self.interact.notify(_(\"Could not copy to clipboard.\"))\n    else:\n        self.interact.notify(_(\"Copied content to clipboard.\"))",
          "triple_sequences": [
            {
              "action_api": "self.get_session_formatted_for_file()",
              "action_description": "Basic read operations for reading (normal reading, binary reading)",
              "action_id": "basic_read_operations",
              "object": "",
              "object_description": "",
              "object_id": "",
              "intention_description": "Access file content",
              "intention_id": "access_file_content"
            },
            {
              "action_api": "pyperclip.copy()",
              "action_description": "Copies specified text to system clipboard",
              "action_id": "copy_to_clipboard",
              "object": "content",
              "object_description": "Clipboard content data",
              "object_id": "clipboard_data",
              "intention_description": "Access clipboard data",
              "intention_id": "access_clipboard_data"
            }
          ]
        }
      ]
    }
  ]
}