{
  "metadata": {
    "package_name": "pyvex-9",
    "original_json_path": "/home2/blue/Documents/PyPIAgent/Codes/code_contexral/codesnippets/benign/pyvex-9.2.149.json",
    "dataset_type": "benign"
  },
  "code_files": [
    {
      "pyfile": "setup.py",
      "full_path": "/home2/blue/Documents/PyPIAgent/Dataset/study/unzip_benign/pyvex-9.2.149/pyvex-9.2.149/setup.py",
      "line_number": "55",
      "type_description": "code-execution",
      "context_snippet": "import os\nimport shutil\nimport subprocess\nimport sys\nimport multiprocessing\nfrom setuptools.errors import LibError\n\nVEX_PATH = os.path.abspath(os.path.join(PROJECT_DIR, \"vex\"))\n\ndef _build_vex():\n    if len(os.listdir(VEX_PATH)) == 0:\n        raise LibError(\n            \"vex submodule not cloned correctly, aborting.\\nThis may be fixed with `git submodule update --init`\"\n        )\n\n    e = os.environ.copy()\n    e[\"MULTIARCH\"] = \"1\"\n    e[\"DEBUG\"] = \"1\"\n\n    if sys.platform == \"win32\":\n        cmd = [\"nmake\", \"/f\", \"Makefile-msvc\", \"all\"]\n    elif shutil.which(\"gmake\") is not None:\n        cmd = [\"gmake\", \"-f\", \"Makefile-gcc\", \"-j\", str(multiprocessing.cpu_count()), \"all\"]\n    else:\n        cmd = [\"make\", \"-f\", \"Makefile-gcc\", \"-j\", str(multiprocessing.cpu_count()), \"all\"]\n\n    try:\n        subprocess.run(cmd, cwd=VEX_PATH, env=e, check=True)\n    except FileNotFoundError as err:\n        raise LibError(\"Couldn't find \" + cmd[0] + \" in PATH\") from err\n    except subprocess.CalledProcessError as err:\n        raise LibError(\"Error while building libvex: \" + str(err)) from err",
      "hash_value": "3726fde2b7f0096d6929a4d0aa71bbae",
      "detection_index": 1,
      "code_snippets": [
        {
          "snippet": "import os\nimport shutil\nimport subprocess\nimport sys\nimport multiprocessing\nfrom setuptools.errors import LibError\n\nVEX_PATH = os.path.abspath(os.path.join(PROJECT_DIR, \"vex\"))\n\ndef _build_vex():\n    if len(os.listdir(VEX_PATH)) == 0:\n        raise LibError(\n            \"vex submodule not cloned correctly, aborting.\\nThis may be fixed with `git submodule update --init`\"\n        )\n\n    e = os.environ.copy()\n    e[\"MULTIARCH\"] = \"1\"\n    e[\"DEBUG\"] = \"1\"\n\n    if sys.platform == \"win32\":\n        cmd = [\"nmake\", \"/f\", \"Makefile-msvc\", \"all\"]\n    elif shutil.which(\"gmake\") is not None:\n        cmd = [\"gmake\", \"-f\", \"Makefile-gcc\", \"-j\", str(multiprocessing.cpu_count()), \"all\"]\n    else:\n        cmd = [\"make\", \"-f\", \"Makefile-gcc\", \"-j\", str(multiprocessing.cpu_count()), \"all\"]\n\n    try:\n        subprocess.run(cmd, cwd=VEX_PATH, env=e, check=True)\n    except FileNotFoundError as err:\n        raise LibError(\"Couldn't find \" + cmd[0] + \" in PATH\") from err\n    except subprocess.CalledProcessError as err:\n        raise LibError(\"Error while building libvex: \" + str(err)) from err",
          "triple_sequences": [
            {
              "action_api": "os.path.abspath()",
              "action_description": "Basic path string operations (getting absolute path, base name, parent directory, splitting and joining paths)",
              "action_id": "path_string_operations",
              "object": "os.path.join(PROJECT_DIR, \"vex\")",
              "object_description": "Path segment",
              "object_id": "path_segment",
              "intention_description": "Construct file or directory path",
              "intention_id": "construct_file_path"
            },
            {
              "action_api": "os.listdir()",
              "action_description": "List directory contents",
              "action_id": "list_directory_contents",
              "object": "VEX_PATH",
              "object_description": "Directory path",
              "object_id": "directory_path",
              "intention_description": "List files in directory",
              "intention_id": "list_directory_files"
            },
            {
              "action_api": "os.environ.copy()",
              "action_description": "Retrieves value of environment variable",
              "action_id": "get_env_var",
              "object": "",
              "object_description": "Environment variable",
              "object_id": "environment_variable",
              "intention_description": "Collect environment variable",
              "intention_id": "collect_environment_variable"
            },
            {
              "action_api": "shutil.which()",
              "action_description": "Checks if specified path exists in filesystem",
              "action_id": "check_path_exists",
              "object": "\"gmake\"",
              "object_description": "Local file or directory name",
              "object_id": "local_file_or_directory_name",
              "intention_description": "Determine presence of required module",
              "intention_id": "determine_required_module_presence"
            },
            {
              "action_api": "multiprocessing.cpu_count()",
              "action_description": "Retrieves operating system information",
              "action_id": "get_os_info",
              "object": "",
              "object_description": "",
              "object_id": "",
              "intention_description": "Get system info",
              "intention_id": "get_system_info"
            },
            {
              "action_api": "subprocess.run()",
              "action_description": "Executes shell command",
              "action_id": "execute_shell_command",
              "object": "cmd",
              "object_description": "Shell command",
              "object_id": "shell_command",
              "intention_description": "Execute command",
              "intention_id": "execute_command"
            }
          ]
        }
      ]
    }
  ]
}