{
  "package_name": "hanaro",
  "is_malicious": false,
  "files_analyzed": 5,
  "malicious_files": 0,
  "file_results": [
    {
      "file_path": "/home2/wenbo/Documents/PyPIAgent/Dataset/latest/unzip_benign/hanaro/hanaro-0.0.1/hanaro/QueuedHandler.py",
      "relative_path": "hanaro-0.0.1/hanaro/QueuedHandler.py",
      "is_malicious": false,
      "malicious_behavior": ""
    },
    {
      "file_path": "/home2/wenbo/Documents/PyPIAgent/Dataset/latest/unzip_benign/hanaro/hanaro-0.0.1/hanaro/__init__.py",
      "relative_path": "hanaro-0.0.1/hanaro/__init__.py",
      "is_malicious": false,
      "malicious_behavior": ""
    },
    {
      "file_path": "/home2/wenbo/Documents/PyPIAgent/Dataset/latest/unzip_benign/hanaro/hanaro-0.0.1/hanaro/utils.py",
      "relative_path": "hanaro-0.0.1/hanaro/utils.py",
      "is_malicious": false,
      "malicious_behavior": ""
    },
    {
      "file_path": "/home2/wenbo/Documents/PyPIAgent/Dataset/latest/unzip_benign/hanaro/hanaro-0.0.1/hanaro/ContextInjectionFilter.py",
      "relative_path": "hanaro-0.0.1/hanaro/ContextInjectionFilter.py",
      "is_malicious": false,
      "malicious_behavior": ""
    },
    {
      "file_path": "/home2/wenbo/Documents/PyPIAgent/Dataset/latest/unzip_benign/hanaro/hanaro-0.0.1/hanaro/ConfigFilter.py",
      "relative_path": "hanaro-0.0.1/hanaro/ConfigFilter.py",
      "is_malicious": false,
      "malicious_behavior": ""
    }
  ],
  "true_label": "benign"
}