{
  "package_name": "libdiva",
  "is_malicious": false,
  "files_analyzed": 5,
  "malicious_files": 0,
  "file_results": [
    {
      "file_path": "/home2/wenbo/Documents/PyPIAgent/Dataset/latest/unzip_benign/libdiva/libdiva-0.1.2/libdiva/farc.py",
      "relative_path": "libdiva-0.1.2/libdiva/farc.py",
      "is_malicious": false,
      "malicious_behavior": ""
    },
    {
      "file_path": "/home2/wenbo/Documents/PyPIAgent/Dataset/latest/unzip_benign/libdiva/libdiva-0.1.2/libdiva/__init__.py",
      "relative_path": "libdiva-0.1.2/libdiva/__init__.py",
      "is_malicious": false,
      "malicious_behavior": ""
    },
    {
      "file_path": "/home2/wenbo/Documents/PyPIAgent/Dataset/latest/unzip_benign/libdiva/libdiva-0.1.2/libdiva/divafile.py",
      "relative_path": "libdiva-0.1.2/libdiva/divafile.py",
      "is_malicious": false,
      "malicious_behavior": ""
    },
    {
      "file_path": "/home2/wenbo/Documents/PyPIAgent/Dataset/latest/unzip_benign/libdiva/libdiva-0.1.2/libdiva/dlt.py",
      "relative_path": "libdiva-0.1.2/libdiva/dlt.py",
      "is_malicious": false,
      "malicious_behavior": ""
    },
    {
      "file_path": "/home2/wenbo/Documents/PyPIAgent/Dataset/latest/unzip_benign/libdiva/libdiva-0.1.2/libdiva/__main__.py",
      "relative_path": "libdiva-0.1.2/libdiva/__main__.py",
      "is_malicious": false,
      "malicious_behavior": ""
    }
  ],
  "true_label": "benign"
}