[
  {
    "pyfile": "clipboard.py",
    "code_snippet": "import typing\n\nimport pyperclip  # type: ignore[import]\n\n\ndef get_paste_buffer() -> str:\n    \"\"\"Get the contents of the clipboard / paste buffer.\n\n    :return: contents of the clipboard\n    \"\"\"\n    pb_str = typing.cast(str, pyperclip.paste())\n    return pb_str\n\n\ndef write_to_paste_buffer(txt: str) -> None:\n    \"\"\"Copy text to the clipboard / paste buffer.\n\n    :param txt: text to copy to the clipboard\n    \"\"\"\n    pyperclip.copy(txt)\n",
    "pattern_analysis": {
      "api_sequence": [
        "pyperclip.paste",
        "pyperclip.copy"
      ],
      "api_sequence_with_args": [
        "pyperclip.paste()",
        "pyperclip.copy(txt)"
      ],
      "mapped_sequence": [
        {
          "api_name": "pyperclip.paste",
          "id": "get_clipboard_text",
          "description": "Retrieves text from system clipboard",
          "first_id": "information_gathering",
          "second_id": "input_monitoring",
          "third_id": "clipboard_operations"
        },
        {
          "api_name": "pyperclip.copy",
          "id": "copy_to_clipboard",
          "description": "Copies specified text to system clipboard",
          "first_id": "information_gathering",
          "second_id": "input_monitoring",
          "third_id": "clipboard_operations"
        }
      ],
      "contextual_code": "import pyperclip  # type: ignore[import]\n\ndef get_paste_buffer() -> str:\n    pb_str = typing.cast(str, pyperclip.paste())\n    return pb_str\n\ndef write_to_paste_buffer(txt: str) -> None:\n    pyperclip.copy(txt)"
    }
  },
  {
    "metadata": {
      "package_name": "cmd2-2.5.11",
      "total_matches": 2
    }
  }
]